{
  "root" : {
    "id" : "70357402-10b1-4da4-b4bb-a7949fb937e1",
    "ruleId" : "FP_BR_29.6",
    "ruleDescription" : "Fastsett BG uten avkorting",
    "operator" : "SEQUENCE",
    "rule" : { }
  },
  "nodes" : [ {
    "id" : "70357402-10b1-4da4-b4bb-a7949fb937e1",
    "ruleId" : "FP_BR_29.6",
    "ruleDescription" : "Fastsett BG uten avkorting",
    "operator" : "SEQUENCE",
    "rule" : { }
  }, {
    "id" : "2641a8a3-1416-488e-a851-035423951370",
    "ruleId" : "FP_BR 29.6.1",
    "ruleDescription" : "Fastsett Brukers Andel og ev arbeidsgivers andel av Brutto beregningsgrunnlag",
    "operator" : "SINGLE",
    "rule" : { }
  }, {
    "id" : "c1eba436-0910-4f0b-8804-f32e2c56e372",
    "ruleId" : "FP_BR 29.6.2",
    "ruleDescription" : "Fastsett Avkortet brukers andel og ev avkortet arbeidsgivers andel",
    "operator" : "SINGLE",
    "rule" : { }
  } ],
  "edges" : [ {
    "source" : "70357402-10b1-4da4-b4bb-a7949fb937e1",
    "target" : "2641a8a3-1416-488e-a851-035423951370"
  }, {
    "source" : "70357402-10b1-4da4-b4bb-a7949fb937e1",
    "target" : "c1eba436-0910-4f0b-8804-f32e2c56e372"
  } ]
}